# 虚拟机字节码执行引擎
物理机的执行引擎直接建立在处理器、缓存、指令集和操作系统层面上，而虚拟机的执行引擎由软件自行实现，可以不受物理条件制约的定制指令集和执行引擎的结构体系。不同的虚拟机实现可能有解释执行和编译执行，还可能有即时编译器，但是从外观来看，所有执行引擎的输入输出都是一致的。

## 运行时栈帧结构
Java虚拟机以方法作为最基本的执行单元，栈帧是用于支持虚拟机进行方法调用和方法执行背后的数据结构，他也是虚拟机运行时数据区中的虚拟机栈的栈元素。每一个栈帧都包括了局部变量表、操作数栈、动态连接、方法返回地址和一些额外的附加信息。在编译Java程序源码的时候，栈帧需要分配多少内存已经被分析计算出来，并且写到方法表的`Code`属性中，并不会受到程序运行期变量数据的影响
- 当前栈帧：只有位于栈顶的方法在运行，也只有栈顶的栈帧有效
- 当前方法：当前栈帧对应的方法

所有字节码指令都只针对当前栈帧进行操作。

### 局部变量表
存放了方法参数和方法内部定义的局部变量。Java程序被编译为Class文件的时候，就在方法的Code属性`max_locals`数据项中确定了该方法的局部变量表需要的最大容量。

局部变量表的容量以变量槽为单位，虚拟机规范没有明确指出一个变量槽应该占用的内存空间大小，只是导向的说每个变量槽都应该能存放一个`boolean`、`byte`、`char`、`short`、`int`、`float`、`reference`、`returnAddress`类型的数据。

对于64位的数据，`long`和`double`会被分配两个连续的变量槽空间，这与`long`和`double`的非原子协定：允许把一次`long`和`double`数据类型读写分为两次32位读写的做法类似。

#### reference
一个对象的引用，虚拟机规范没有固定长度和结构，只规定了功能：
1. 根据引用可以直接或者间接的查找到对象在Java堆中的数据地址或者索引
2. 根据引用查找到对象所属数据类型在方法区中存储的类型信息

#### returnAddress
目前已经很少见了，是为`jsr`，`jsr_w`，`ret`服务的，指向了一条字节码指令的地址，曾经有虚拟机用这些指令处理异常跳转，现在改为采用异常表实现了

虚拟机通过索引定位的方式使用局部变量表，索引值的范围是从0到局部变量表的最大变量槽数量。如果访问32位数据，索引`N`就代表使用了第`N`个变量槽，如果访问64位数据，索引`N`就代表了使用第`N`和`N+1`个变量槽。

当一个方法被调用时，虚拟机使用局部变量表来完成实参到形参的传递。如果是实例方法，第0位索引的变量槽默认是方法所属对象实例的引用，也就是`this`。

为了节省栈帧耗费的内存，变量槽是可以重用的，方法体中的变量作用域并不一定覆盖了整个方法体，如果当前字节码PC计数器超出了某个变量的作用域，那这个变量对应的变量槽就可以交给其他变量来使用。这样会对垃圾收集行为有一些影响。当某些变量离开他的作用域，如果变量槽没有被其他变量重用，那么这个变量就不会被收集，因为局部变量表还存着他的引用，虽然以后这个变量以后也不会再使用了，所以给变量赋值为`null`来帮助`GC`的行为是可以理解的，但是实际上将变量设置为`null`的行为很可能被编译优化当作无效操作消除掉。

注意局部变量不会赋默认值，下面的代码不能运行：
```java
public static void main(String[] args) {
	int a;
	System.out.println(a);
}
```

### 操作数栈
最大深度也在编译的时候被写入到Code属性的`max_stacks`数据项之中，操作数栈中的每一个元素都可以是包括`long`和`double`的任意Java数据类型。

当一个方法刚刚开始执行的时候，这个方法的操作数栈是空的，在方法的执行过程中，会有各种字节码指令进行入栈出栈的动作来帮助运算，或者调用其他方法的时候利用操作数栈来进行方法参数的传递。概念模型中两个不同的栈帧作为不同方法的虚拟机栈的元素是完全独立的，但是大多数虚拟机的实现会让栈帧出现一部分重叠，让下面栈帧的部分操作数栈和上面栈帧的部分局部变量表重叠在一起，可以节约空间并且减少额外的参数复制传递。
![[Pasted image 20220509220538.png]]


### 动态连接
每个栈帧都包含一个指向运行时常量池中该栈帧所属方法的引用，这个引用为了支持方法调用中的动态连接。字节码中的方法调用指令就以常量池里指向方法的符号引用为参数。这些符号引用一部分会在类加载阶段或者第一次使用的时候转化为直接引用，这叫静态解析。有一部分符号引用将在每一次运行期间转化为直接引用，这部分就叫动态连接。

### 方法返回地址
两种方式退出方法：
1. 执行引擎遇到任意一个方法返回的字节码指令，即正常调用完成
2. 方法执行过程中遇到了异常，而且这个异常在方法体内没有处理妥当，即异常调用完成
	- 没有返回值

方法退出之后，必须返回到最初方法被调用时的位置。方法返回时可能需要在栈帧中保存一些信息，用来帮助恢复他的上层主调方法的执行状态。
1. 方法正常退出时：主调方法的PC计数器的值可以作为返回地址
2. 方法异常退出时，返回地址要通过异常处理表来确定

方法退出的过程实际上等同于把当前栈帧出栈，因此退出时可能执行的操作：
1. 回复上层方法的局部变量表和操作数栈
2. 把返回值压入调用者栈帧的操作数栈中
3. 调整PC计数器的值来指向方法调用指令后面的一条指令

### 附加信息
Java虚拟机规范允许虚拟机实现一些规范里没有描述的信息到栈帧，取决于实现

## 方法调用
方法调用不等于方法中的代码被执行，唯一的任务是确定被调用方法的版本。一切方法调用在Class文件中储存的都只是符号引用，而不是方法在实际运行时内存布局中的入口地址。这个方法给Java带来了更强大的动态扩展能力，但是Java的方法调用更复杂。

### 解析
所有方法调用的目标方法在Class文件里面都是一个常量池中的符号引用，在类加载的解析阶段，会将其中一部分符号引用转化为直接引用。前提是：**方法在程序真正运行之前就有一个可确定的调用版本，并且这个方法的调用版本在运行期不可改变**。也就是说调用目标在编译器进行编译的时候已经确定下来。主要有静态方法和私有方法两大类。

调用不同的方法，有五种方法调用字节码指令：
1. `invokestatic`：调用静态方法
2. `invokespecial`：调用实例构造器`<init>()`方法，私有方法和父类方法
3. `invokevirtual`：调用虚方法
4. `invokeinterface`：调用接口方法，运行时确定一个实现该接口的对象
5. `invokedynamic`：先在运行时动态解析出调用点限定符所引用的方法，然后再执行

前四个调用指令的分派逻辑固化在Java虚拟机内部，最后一个指令的分派逻辑是由用户设定的引导方法决定的。

只要能被`invokestatic`和`invokespecial`指令调用的方法都可以在解析阶段确定唯一的版本
1. 静态方法
2. 私有方法
3. 实例构造器
4. 父类方法
5. final修饰的方法：`invokevirtual`调用，历史原因

这些方法被称为非虚方法，其他方法被称为虚方法。

### 分派
Java是面向对象的程序语言，分派调用揭示了多态性特征的一些最基本的实现，比如重载和重写

#### 静态分派
`Method Overload Resolution`，应该属于解析的一部分。
1. 静态类型、外观类型：引用的类型
2. 实际类型、运行时类型：对象的实际类型

静态分派指的是根据静态类型来决定方法执行版本的分派动作。最典型应用表现就是方法重载，他发正在编译阶段，实际上不是虚拟机来执行的分派，是编译器来确定的，编译器会挑选最合适的。
```java
public class Overload {
	public static void sayHello(int arg) {
		System.out.println("hello int");
	}
	public static void sayHello(char arg) {
		System.out.println("hello long");
	}

	public static void main(String[] args) {
		sayHello('a');
	}
}
```
#### 动态分派
在动态分派中，选择调用方法的版本是根据实际类型决定的，最典型的就是多态，可以用父类的引用调用子类的方法。
```bash
aload
invokevirtual
```
`aload`指令把对象A的引用压入栈顶，对象A是要执行方法的所有者，称为接收者。`invokevirtual`
指令是方法调用指令，他的运行时解析过程大概分为以下几步：
1. 找到操作数栈栈顶的第一个元素所指对象的实际类型，记作C
2. 在C中找到与常量中的描述符和简单名称都相符的方法，
	- 权限校验，通过返回
	- 没通过返回`IllegalAccessError`
3. 没找到，按继承关系从下往上依次对C的各个父类进行第二步的搜索和验证过程
4. 最后没找到，抛出`AbstractMethodError`

正是因为`invokevirtual`指令的第一步是在运行期确定接受者的实际类型，所以会根据接受者的实际类型来选择方法版本。这也说明类的字段是没有多态的，当子类声明了与父类同名的字段时，子类的字段会遮蔽父类的同名字段。

#### 单分派和多分派
方法的接受者与方法的参数统称为方法的宗量。根据分派基于多少种宗量可以将分派划分为单分派和多分派两种。
1. 单分派：根据一个宗量对目标方法进行选择
2. 多分派：根据多于一个宗量对目标方法进行选择

Java虚拟机的静态分派属于多分派类型，会根据静态类型和方法参数两个宗量进行选择。动态分配的过程中，目标方法的签名已经在编译期决定了，只需要根据接受者的实际类型选择方法，所以动态分派是单分派类型。

```java
public class Dispatcher {
    static class QQ {}
    static class _360 {}

    public static class Father {
        public void hardChoice(QQ arg) {
            System.out.println("father choose QQ");
        }

        public void hardChoice(_360 arg) {
            System.out.println("father choose _360");
        }
    }

    public static class Son extends Father {
        @Override
        public void hardChoice(QQ arg) {
            System.out.println("son choose QQ");
        }

        @Override
        public void hardChoice(_360 arg) {
            System.out.println("son choose 360");
        }
    }

    public static void main(String[] args) {
        Father father = new Father();
        Father son = new Son();
        father.hardChoice(new _360());
        son.hardChoice(new QQ());
    }
}
```
```bash
public static void main(java.lang.String[]);
  Code:
   Stack=3, Locals=3, Args_size=1
   0:   new             #2; //class Dispatcher$Father
   3:   dup
   4:   invokespecial   #3; //Method Dispatcher$Father."<init>":()V
   7:   astore_1
   8:   new             #4; //class Dispatcher$Son
   11:  dup
   12:  invokespecial   #5; //Method Dispatcher$Son."<init>":()V
   15:  astore_2
   16:  aload_1
   17:  new             #6; //class Dispatcher$_360
   20:  dup
   21:  invokespecial   #7; //Method Dispatcher$_360."<init>":()V
   24:  invokevirtual   #8; //Method Dispatcher$Father.hardChoice:(LDispatcher$_360;)V
   27:  aload_2
   28:  new             #9; //class Dispatcher$QQ
   31:  dup
   32:  invokespecial   #10; //Method Dispatcher$QQ."<init>":()V
   35:  invokevirtual   #11; //Method Dispatcher$Father.hardChoice:(LDispatcher$QQ;)V
   38:  return
```
方法分派的步骤如下：
1. 静态分派：编译时
	1. 确定方法接收者，变量的静态类型是Father，在class文件中写Father类方法的符号引用
	2. 对于方法参数，按照静态类型匹配的原则，找到各自的方法
2. 动态分派：执行时
	- `son.hardChoice(new QQ());`：发现son的实际类型是Son，会调用Son类中的方法
	- `father.hardChoice(new _360());`：father的实际类型就是Father

#### 动态分派的实现
具体的实现可能在各种虚拟机之前会有一些差别。

动态分派执行非常频繁，方法版本的选择过程需要运行时在接受者类型的方法元数据中搜索合适的目标方法。因此虚拟机一般不会频繁的反复搜索类型元数据，一种常见的优化手段是为类型在方法区中建立一个虚方法表，使用虚方法表来提高性能。

> 1. `Virtual Method Table`：虚方法表
> 2. `Interface Method Table`：接口方法表

虚方法表中存放着各个方法的实际入口地址。
1. 如果某个方法在子类中没有被重写，那子类的虚方法表中的入口地址和父类相同方法的入口地址一致，都指向父类的实现入口。
2. 如果子类中重写了这个方法，子类虚方法表中的地址也会被替换为子类实现版本的入口地址。

具有相同签名的方法，在父类、子类的虚方法表中应当具有一样的索引序号。当类型变换的时候，仅仅需要变更查找的虚方法表，就可以从不同的虚方法表中按索引转换出所需的入口地址。

虚方法表一般在类加载的连接阶段初始化，准备了类的变量初始值后，虚拟机会把该类的虚方法表也一同初始化完毕。

还有其他的优化方式
- 类型继承关系分析
- 守护内联
- 内联缓存

## 动态类型语言支持
什么是动态类型语言？关键特征是他的类型检查的主体过程是在运行期而不是编译期进行的。核心特征是：变量无类型而变量值才有类型。

### java.lang.invoke包
主要目的是解决单纯靠符号引用来确定调用的目标方法导致的资源压力和性能问题，提供了一种新的动态确定目标方法的机制，称为方法句柄。Java语言之前没有办法把一个函数作为参数进行传递，有了方法句柄之后，就可以拥有类似函数指针或者委托的方法别名这样的工具。
```java
import static java.lang.invoke.MethodHandles.lookup;

import java.lang.invoke.MethodHandle;
import java.lang.invoke.MethodType;

public class MethodHandleTest {

    static class ClassA {
        public void println(String s) {
            System.out.println(s);
        }
    }

    public static MethodHandle getPrintMH(Object receiver) throws Throwable {
        // 包含了方法的返回值和具体参数
        MethodType mt = MethodType.methodType(void.class, String.class);
        // 在指定类中查找了类中符合给定的方法名称、方法类型并且符合权限的方法句柄
        // 这里调用虚方法，按照Java语言的规则，方法的第一个参数是隐式的，代表接受者
        // 这个参数以前放在参数列表中传递，现在用 bindTo 方法
        return lookup().findVirtual(receiver.getClass(), "println", mt)
				       .bindTo(receiver);
    }

    public static void main(String[] args) throws Throwable {
        Object obj = System.currentTimeMillis() % 2 == 0 
	        ? System.out : new ClassA();
	    // 无论obj是那个实现类，都能正确调用到println方法
        getPrintMH(obj).invokeExact("HelloWorld!");
    }
}
```
方法`getPrintlnMH()`实际上模拟了`invokevirtual`指令的执行过程，只不过分派逻辑不是固化在Class文件的字节码上，而是通过一个用户设计的Java方法来实现。方法句柄和反射有区别：
1. 反射模拟Java代码层次的方法调用，方法句柄是在模拟字节码层次的方法调用，`Lookup`方法
	- `findStatic()`：`invokestatic`
	- `findVirtual()`：`invokevirtual`
	- `findSpecial()`：`invokeinterface`
2. 反射比方法句柄包含的信息更多。
3. 虚拟机在方法调用方面做的优化，方法句柄也可以用相似的方法去支持，
	- 反射不可能实施优化措施

### invokedynamic指令
某种意义上来说`invokedynamic`指令和`MethodHandle`机制的作用是一致的，每一处含有`invokedynamic`指令的位置都称作动态调用点。这条指令的第一个参数不是代表方法符号引用的`CONSTANT_Methodtref_info`常量，而是变为JDK 7新加入的`CONSTANT_InvokeDynamic_info`常量。从这个常量中可以得到三项信息：
1. 引导方法：`BootstrapMethods`属性中
2. 方法类型
3. 方法名称

引导方法有固定的参数，并且返回值规定是`java.lang.invoke.CallSite`对象，代表了真正要执行的目标方法调用。根据`CONSTANT_InvokeDynamic_info`常量中提供的信息，虚拟机可以找到并且执行引导方法，从而获得一个`CallSite`对象，最终调用到要执行的目标方法上。

由于`invokedynamic`指令面向的主要服务对象是其他Java虚拟机之上的其他动态类型语言，所以光靠Javac的话，在JDK 7甚至还没办法生成带有`invokedynamic`指令的字节码，到了JDK 8引入Lambda表达式和接口默认方法，Java程序才享受到了`invokedynamic`指令的一点好处。
![[Pasted image 20220511112403.png]]
引导方法是我们为设置调用过程而编写的一段普通的Java代码，执行引导方法得到的`CallSite`实例中封装了一下信息：
1. 指向JVM应该执行的实际逻辑的指针，`Method Handle`
2. 表示返回的`CallSite`有效性的条件

从现在开始，每次JVM再次看见这个指令都会跳过慢路径并且直接调用底层的可执行文件。直到`CallSite`中的条件发生变化，再重新执行慢路径。

#### lambda
`lambda`的实现过程为
1. 编译时
    - `Lambda`表达式会生成一个方法，方法实现了表达式的代码逻辑
    - 生成`invokedynamic`指令， 调用`bootstrap`方法
2. 运行时
    - `invokedynamic`指令调`bootstrap`方法。 它会返回一个`CallSite`
    - 此`CallSite`返回目标类型的一个匿名实现类， 此类关联编译时产生的方法
    - `lambda`表达式调用时会调用匿名实现类关联的方法

```java
public class Main { 
    public static void main(String[] args) {
        long lengthyColors = List.of("Red", "Green", "Blue")
	        .stream().filter(c -> c.length() > 3).count();
    }
}
// 对应的字节码
javap -c -p Main
// truncated
// class names are simplified for the sake of brevity 
// for instance, Stream is actually java/util/stream/Stream
0: ldc               #7     // String Red
2: ldc               #9     // String Green
4: ldc               #11    // String Blue
6: invokestatic      #13    // InterfaceMethod List.of:(LObject;LObject;)LList;
9: invokeinterface   #19,1  // InterfaceMethod List.stream:()LStream;
14: invokedynamic    #23,0  // InvokeDynamic #0:test:()LPredicate;
19: invokeinterface  #27,2  // InterfaceMethod Stream.filter:(LPredicate;)LStream;
24: invokeinterface  #33,1  // InterfaceMethod Stream.count:()J
29: lstore_1
30: return
```

同时，Java编译器还生成了以下静态方法，实际上就是`lambda`方法实例
```java
private static boolean lambda$main$0(java.lang.String);
    Code:
       0: aload_0
       1: invokevirtual #37          // Method java/lang/String.length:()I
       4: iconst_3
       5: if_icmple     12
       8: iconst_1
       9: goto          13
      12: iconst_0
      13: ireturn
```
所有`lambda`的`Bootstrap`方法都是`LambdaMetafactory`类中的元工厂静态方法
```java
public static CallSite metafactory(MethodHandles.Lookup caller,
								   String invokedName,
								   MethodType invokedType,
								   MethodType samMethodType,
								   MethodHandle implMethod,
								   MethodType instantiatedMethodType)
            throws LambdaConversionException {
    AbstractValidatingLambdaMetafactory mf;
    mf = new InnerClassLambdaMetafactory(caller, invokedType,
	                                    invokedName, samMethodType,
                                        implMethod, instantiatedMethodType,
                                        false, EMPTY_CLASS_ARRAY, EMPTY_MT_ARRAY);
	mf.validateMetafactoryArgs();
	return mf.buildCallSite();
}
``` 
1. `caller`: 由JVM提供的`lookup context`
2. `invokedName`: JVM提供的`NameAndType`
3. `invokedType`: JVM提供的期望的`CallSite`类型：`MutableCallSite` 和 `VolatileCallSite`
4. `samMethodType`: 函数式接口定义的方法的签名
5. `implMethod`: 编译时产生的那个实现方法
6. `instantiatedMethodType`: 强制的方法签名和返回类型
	- 一般和`samMethodType`相同或者是它的一个特例

上面的代码基本上是`InnerClassLambdaMetafactory.buildCallSite`的包装
```java
CallSite buildCallSite() throws LambdaConversionException {
   final Class<?> innerClass = spinInnerClass();
   if (invokedType.parameterCount() == 0) {
	   //... 调用构造函数初始化一个SAM的实例
	   return new ConstantCallSite(MethodHandles.constant(samBase, inst));
   } else {
	   UNSAFE.ensureClassInitialized(innerClass);
	   return new ConstantCallSite(
		   MethodHandles.Lookup.IMPL_LOOKUP
		   .findStatic(innerClass, NAME_FACTORY, invokedType));
   }
}
```
其中`spinInnerClass`调用`asm`框架动态的产生SAM的实现类， 这个实现类的的方法将会调用编译时产生的那个实现方法。

## 基于栈的字节码解释执行引擎
### 基于栈的指令集和基于寄存器的指令集
Javac 编译器输出的字节码指令流，基本上是一种基于栈的指令集架构，字节码指令流里面的大部分指令都是零地址指令，他们依赖操作数栈进行工作。另外一套常用的指令集架构是基于寄存器的指令集，最典型的就是X86的二地址指令集。

基于栈的指令集架构的主要优点是可移植，因为寄存器由硬件直接提供，程序直接依赖这些硬件寄存器则不可避免地要受硬件制约。如果使用栈架构的指令集，用户程序不会直接用到这些寄存器，那就可以由虚拟机实现来自行决定把一些访问最频繁的数据放到寄存器中来获得更好的性能。

主要缺点是理论上执行速度会慢一点，不过如果经过即时编译器输出成物理机上的汇编指令流，那就与虚拟机采用那种指令集架构没什么关系了。


